{
  "asset_count": 6,
  "by_asset": {
    "412758873": {
      "count": 0,
      "name": "duetos-kernel-debug.elf",
      "release_tag": "latest-debug"
    },
    "412758874": {
      "count": 0,
      "name": "duetos-debug.iso",
      "release_tag": "latest-debug"
    },
    "412758876": {
      "count": 0,
      "name": "SHA256SUMS.txt",
      "release_tag": "latest-debug"
    },
    "412758900": {
      "count": 0,
      "name": "duetos-release.iso",
      "release_tag": "latest-release"
    },
    "412758903": {
      "count": 0,
      "name": "duetos-kernel-release.elf",
      "release_tag": "latest-release"
    },
    "412758904": {
      "count": 0,
      "name": "SHA256SUMS.txt",
      "release_tag": "latest-release"
    }
  },
  "delta_this_run": 0,
  "lifetime_total": 1,
  "live_assets_total": 0,
  "repo": "Krilliac/DuetOS",
  "snapshot_at": "2026-05-05T15:34:15+00:00"
}
